setuptools_template/__init__.py
setuptools_template/__main__.py
setuptools_template/__version__.py
setuptools_template/main.py
setuptools_template-0.1.3.dist-info/METADATA
setuptools_template-0.1.3.dist-info/WHEEL
setuptools_template-0.1.3.dist-info/entry_points.txt
setuptools_template-0.1.3.dist-info/top_level.txt
setuptools_template-0.1.3.dist-info/RECORD
